.testr.conf
.travis.yml
AUTHORS
ChangeLog
Makefile
README.rst
circle.yml
requirements.txt
setup.cfg
setup.py
tox.ini
libindic/utils/__init__.py
libindic/utils/charmap.py
libindic/utils/langdetect.py
libindic_utils.egg-info/PKG-INFO
libindic_utils.egg-info/SOURCES.txt
libindic_utils.egg-info/dependency_links.txt
libindic_utils.egg-info/namespace_packages.txt
libindic_utils.egg-info/not-zip-safe
libindic_utils.egg-info/pbr.json
libindic_utils.egg-info/top_level.txt
tests/__init__.py
tests/test_libindic_utils.py