Metadata-Version: 1.1
Name: libindic-utils
Version: 1.0.3
Summary: Common functions for libindic and related modules
Home-page: https://libindic.org
Author: SILPA Developers
Author-email: silpa-discuss@nongnu.org
License: LGPL-2.1+
Platform: UNKNOWN
Classifier: License :: DFSG approved
Classifier: License :: OSI Approved :: GNU Lesser General Public License v2 or later (LGPLv2+)
Classifier: Operating System :: OS Independent
Classifier: Intended Audience :: Developers
Classifier: Intended Audience :: Information Technology
Classifier: Programming Language :: Python
